{
    "info": {
        "stock": "kodak_gold_200",
        "name": "Kodak Gold 200",
        "type": "negative",
        "color": true,
        "densitometer": "status_M",
        "log_sensitivity_density_over_min": 0.2,
        "reference_illuminant": "D55",
        "viewing_illuminant": "D50"
    },
    "data": {
        "log_sensitivity": [
            [
                NaN,
                NaN,
                1.188442115038625
            ],
            [
                NaN,
                0.8833984230546016,
                1.5433605477092662
            ],
            [
                0.610200958897177,
                1.2220213345310267,
                1.9875250291067164
            ],
            [
                0.5348966640891096,
                1.2139003603913534,
                2.1123596773433095
            ],
            [
                0.3862193876547144,
                1.1224568834015947,
                2.0858223755833287
            ],
            [
                0.2351822016180397,
                1.0261232903182063,
                2.0883323724211906
            ],
            [
                0.10814699820690366,
                0.9350224987807918,
                2.1441327710892777
            ],
            [
                0.02700740023236826,
                0.9180997981052171,
                2.121098651591517
            ],
            [
                0.0003515028909839353,
                0.9191146391902675,
                2.1743126966882675
            ],
            [
                0.0046459935378281485,
                0.9360616101304532,
                2.3489085119276307
            ],
            [
                -0.019118222485665047,
                1.1576267954352633,
                2.0377301605565186
            ],
            [
                0.08674669178080374,
                1.4710023037296287,
                0.9443644094201064
            ],
            [
                0.19658706535536508,
                1.6614977178027281,
                0.36430755385570046
            ],
            [
                0.29699684897907264,
                1.751115890380242,
                NaN
            ],
            [
                0.3960091129909981,
                1.861919760395283,
                NaN
            ],
            [
                0.4604787569511869,
                2.0127973114550377,
                NaN
            ],
            [
                0.5325548315764138,
                2.181970828247624,
                NaN
            ],
            [
                0.6248231660324272,
                2.231995428525963,
                NaN
            ],
            [
                0.7739916271280948,
                2.1513931901108534,
                NaN
            ],
            [
                0.8888324763427878,
                1.8807172476711465,
                NaN
            ],
            [
                1.1763657890880586,
                1.4879345713642131,
                NaN
            ],
            [
                1.3772500478606602,
                0.6838197524132537,
                NaN
            ],
            [
                1.5202383808526194,
                NaN,
                NaN
            ],
            [
                1.6332352697457775,
                NaN,
                NaN
            ],
            [
                1.7651368860912664,
                NaN,
                NaN
            ],
            [
                1.8740491301880444,
                NaN,
                NaN
            ],
            [
                2.047052290566867,
                NaN,
                NaN
            ],
            [
                2.2017627510494315,
                NaN,
                NaN
            ],
            [
                2.138832078123583,
                NaN,
                NaN
            ],
            [
                1.6166756460271565,
                NaN,
                NaN
            ],
            [
                1.1356786077399472,
                NaN,
                NaN
            ],
            [
                NaN,
                NaN,
                NaN
            ],
            [
                NaN,
                NaN,
                NaN
            ],
            [
                NaN,
                NaN,
                NaN
            ],
            [
                NaN,
                NaN,
                NaN
            ],
            [
                NaN,
                NaN,
                NaN
            ],
            [
                NaN,
                NaN,
                NaN
            ],
            [
                NaN,
                NaN,
                NaN
            ],
            [
                NaN,
                NaN,
                NaN
            ],
            [
                NaN,
                NaN,
                NaN
            ],
            [
                NaN,
                NaN,
                NaN
            ]
        ],
        "wavelengths": [
            380.0,
            390.0,
            400.0,
            410.0,
            420.0,
            430.0,
            440.0,
            450.0,
            460.0,
            470.0,
            480.0,
            490.0,
            500.0,
            510.0,
            520.0,
            530.0,
            540.0,
            550.0,
            560.0,
            570.0,
            580.0,
            590.0,
            600.0,
            610.0,
            620.0,
            630.0,
            640.0,
            650.0,
            660.0,
            670.0,
            680.0,
            690.0,
            700.0,
            710.0,
            720.0,
            730.0,
            740.0,
            750.0,
            760.0,
            770.0,
            780.0
        ],
        "density_curves": [
            [
                NaN,
                NaN,
                NaN
            ],
            [
                NaN,
                NaN,
                NaN
            ],
            [
                NaN,
                NaN,
                NaN
            ],
            [
                NaN,
                NaN,
                NaN
            ],
            [
                NaN,
                NaN,
                NaN
            ],
            [
                NaN,
                NaN,
                NaN
            ],
            [
                NaN,
                NaN,
                NaN
            ],
            [
                NaN,
                NaN,
                NaN
            ],
            [
                NaN,
                NaN,
                NaN
            ],
            [
                NaN,
                NaN,
                NaN
            ],
            [
                NaN,
                NaN,
                NaN
            ],
            [
                NaN,
                NaN,
                NaN
            ],
            [
                NaN,
                NaN,
                NaN
            ],
            [
                NaN,
                NaN,
                NaN
            ],
            [
                NaN,
                NaN,
                NaN
            ],
            [
                NaN,
                NaN,
                NaN
            ],
            [
                NaN,
                NaN,
                NaN
            ],
            [
                NaN,
                NaN,
                NaN
            ],
            [
                NaN,
                NaN,
                NaN
            ],
            [
                NaN,
                NaN,
                NaN
            ],
            [
                NaN,
                NaN,
                NaN
            ],
            [
                NaN,
                NaN,
                NaN
            ],
            [
                NaN,
                NaN,
                NaN
            ],
            [
                NaN,
                NaN,
                NaN
            ],
            [
                NaN,
                NaN,
                NaN
            ],
            [
                NaN,
                NaN,
                NaN
            ],
            [
                NaN,
                NaN,
                NaN
            ],
            [
                NaN,
                NaN,
                NaN
            ],
            [
                NaN,
                NaN,
                NaN
            ],
            [
                NaN,
                NaN,
                NaN
            ],
            [
                NaN,
                NaN,
                NaN
            ],
            [
                NaN,
                NaN,
                NaN
            ],
            [
                NaN,
                NaN,
                NaN
            ],
            [
                NaN,
                NaN,
                NaN
            ],
            [
                NaN,
                NaN,
                NaN
            ],
            [
                NaN,
                NaN,
                NaN
            ],
            [
                NaN,
                NaN,
                NaN
            ],
            [
                NaN,
                NaN,
                NaN
            ],
            [
                NaN,
                NaN,
                NaN
            ],
            [
                NaN,
                NaN,
                NaN
            ],
            [
                NaN,
                NaN,
                NaN
            ],
            [
                NaN,
                NaN,
                NaN
            ],
            [
                NaN,
                NaN,
                NaN
            ],
            [
                NaN,
                NaN,
                NaN
            ],
            [
                NaN,
                NaN,
                NaN
            ],
            [
                NaN,
                NaN,
                NaN
            ],
            [
                0.253582750922147,
                0.6591310634748553,
                0.9931682939438404
            ],
            [
                0.2539159135263239,
                0.6594524135120317,
                0.9929070473611539
            ],
            [
                0.25544660190733054,
                0.6609773226761237,
                0.9909044138734131
            ],
            [
                0.25728791213953545,
                0.6629065716303247,
                0.9875531167982924
            ],
            [
                0.2585693141146741,
                0.664454333800425,
                0.983247111442447
            ],
            [
                0.25921367667227657,
                0.6654837335266,
                0.9784400495620023
            ],
            [
                0.2602683455881882,
                0.6667788675249244,
                0.9736690662932637
            ],
            [
                0.2621967392714902,
                0.6687567752313525,
                0.9693255407416151
            ],
            [
                0.2642678218444174,
                0.6710541642772931,
                0.9655301591606081
            ],
            [
                0.266025261384647,
                0.6734345454843503,
                0.9625783876252432
            ],
            [
                0.26790678810977453,
                0.6761272945329351,
                0.9612206508073571
            ],
            [
                0.2702779305177339,
                0.6793350998968103,
                0.9618910426150067
            ],
            [
                0.27295152334291367,
                0.6830038091376225,
                0.9639459432082127
            ],
            [
                0.27577201404347335,
                0.6870712890553495,
                0.966734961653546
            ],
            [
                0.2790551776201731,
                0.6916118340568169,
                0.9702775018330217
            ],
            [
                0.2830978462203569,
                0.69671468142754,
                0.9746973713272503
            ],
            [
                0.2876061116697624,
                0.7023936492270406,
                0.9798933468329444
            ],
            [
                0.29221775474438283,
                0.708650483747588,
                0.9857191852219676
            ],
            [
                0.2971998604159682,
                0.7155470617370048,
                0.9921537590380801
            ],
            [
                0.30297908028791487,
                0.7231473029687231,
                0.9992132530105478
            ],
            [
                0.30939134358171294,
                0.7313549647490994,
                1.0068402885361345
            ],
            [
                0.3160464651505863,
                0.74001551069466,
                1.0149496394534507
            ],
            [
                0.3231055806861592,
                0.7491548791724789,
                1.0235281154356268
            ],
            [
                0.3310222080102434,
                0.7588930606278925,
                1.0326091860795945
            ],
            [
                0.33974826866397023,
                0.7691631722482168,
                1.0422804360836293
            ],
            [
                0.34887496978286536,
                0.7797659624179385,
                1.0526602019129592
            ],
            [
                0.3582676283113167,
                0.7906416799551942,
                1.0636895217077313
            ],
            [
                0.36805107440150275,
                0.8018596150580002,
                1.0751533117701129
            ],
            [
                0.3783192600155064,
                0.8134162037741925,
                1.087074954921165
            ],
            [
                0.3891191957592323,
                0.8252220635863113,
                1.0997522084144566
            ],
            [
                0.4004771611819804,
                0.8373437168098318,
                1.1132092461740255
            ],
            [
                0.41239220740073174,
                0.8500728459437067,
                1.1270604298373392
            ],
            [
                0.4247438461821214,
                0.8633305537089362,
                1.1411174381939881
            ],
            [
                0.43720293606124117,
                0.8763480507577079,
                1.155600021844426
            ],
            [
                0.44964932412469893,
                0.8888529706111086,
                1.1706957452759257
            ],
            [
                0.4624806136999292,
                0.9018477594782114,
                1.1864249807547131
            ],
            [
                0.47603212760461977,
                0.9160352017648679,
                1.202691699861666
            ],
            [
                0.4902606899740368,
                0.9307692652041184,
                1.2191331408296944
            ],
            [
                0.5049852694935698,
                0.945385976243108,
                1.2354850570436795
            ],
            [
                0.5197664659008413,
                0.9600254996699464,
                1.2520141590348532
            ],
            [
                0.534230389442397,
                0.9749517910339461,
                1.2690024923064762
            ],
            [
                0.5485850909339681,
                0.9901511373911929,
                1.2862380063471763
            ],
            [
                0.5631600880316635,
                1.0055280538510216,
                1.3034130986541264
            ],
            [
                0.5779914973782745,
                1.020983356066629,
                1.3205150101065992
            ],
            [
                0.5929926592576246,
                1.0364390441990243,
                1.3376306307987036
            ],
            [
                0.6079724624490854,
                1.0519943784213313,
                1.3547653761592746
            ],
            [
                0.6227184320736805,
                1.0678038803199783,
                1.3718811327225071
            ],
            [
                0.6373081618651124,
                1.0837260068818892,
                1.3888881431171478
            ],
            [
                0.6519763965825704,
                1.0994676115966224,
                1.4056786235675978
            ],
            [
                0.6667452436755738,
                1.1150786389889886,
                1.4223210456669002
            ],
            [
                0.6814809972520093,
                1.1308497378190097,
                1.4390082078708164
            ],
            [
                0.6961153655771746,
                1.1467722305810846,
                1.4558041753525581
            ],
            [
                0.710646109926048,
                1.162564293459853,
                1.4726530642578788
            ],
            [
                0.7251409387952742,
                1.1781854009332935,
                1.489542473489384
            ],
            [
                0.7397427900183654,
                1.1938792643081526,
                1.506516243250393
            ],
            [
                0.7544915211154067,
                1.2096908698232116,
                1.5236788309284877
            ],
            [
                0.7692744090932371,
                1.2253609352491976,
                1.541217209556277
            ],
            [
                0.7840214580852525,
                1.240785373690877,
                1.5593539262451461
            ],
            [
                0.7987597940890906,
                1.2561785029218935,
                1.5783629154569958
            ],
            [
                0.8135093811882806,
                1.2716957782952796,
                1.5983398980127237
            ],
            [
                0.8282515431382353,
                1.28728645349474,
                1.6189683145563347
            ],
            [
                0.8429812960008667,
                1.3029053711126697,
                1.6399150288678437
            ],
            [
                0.8577476862799036,
                1.3186034005761755,
                1.6609598142550475
            ],
            [
                0.8725888171276787,
                1.3344008393323925,
                1.6818096966575846
            ],
            [
                0.8874680587351031,
                1.3501446227700904,
                1.701833726066517
            ],
            [
                0.9023392550521238,
                1.3657024110469032,
                1.720431851925913
            ],
            [
                0.9171913372287775,
                1.3812237102570757,
                1.7375090043764945
            ],
            [
                0.932029704203938,
                1.3969038562285951,
                1.7531656414536543
            ],
            [
                0.9468972335048053,
                1.4127175032195558,
                1.7677912912523248
            ],
            [
                0.9618407216169832,
                1.428556433876537,
                1.7818559629851922
            ],
            [
                0.9768278492215966,
                1.4443084186093302,
                1.795614405507199
            ],
            [
                0.9917965925908911,
                1.4598800333101245,
                1.8092192768166524
            ],
            [
                1.0067648317461233,
                1.4753926183085677,
                1.8228198394343464
            ],
            [
                1.0217940111133685,
                1.4910752621405774,
                1.836571714184187
            ],
            [
                1.0368895620016085,
                1.5068792430460174,
                1.8507438825186706
            ],
            [
                1.0520140523090924,
                1.5225592917567545,
                1.865672702680873
            ],
            [
                1.067111541229847,
                1.538077614967018,
                1.8813635802500703
            ],
            [
                1.0821135824116426,
                1.5535885114692285,
                1.897518881954749
            ],
            [
                1.097060019140367,
                1.5691409878136715,
                1.913949822817811
            ],
            [
                1.1121130019503807,
                1.5846571165633985,
                1.9306060545594843
            ],
            [
                1.1273185322224966,
                1.600157686175922,
                1.9474678555103364
            ],
            [
                1.1425478791850905,
                1.6158126104175679,
                1.9645476893094915
            ],
            [
                1.1577360447680647,
                1.6316301806175895,
                1.9817961027469313
            ],
            [
                1.1729556355233377,
                1.6473104668376246,
                1.9990489461260808
            ],
            [
                1.1882554679736776,
                1.662717403217334,
                2.016197321870117
            ],
            [
                1.203598907971235,
                1.6781546221638477,
                2.0332831589597036
            ],
            [
                1.2189371138414258,
                1.6938245420761195,
                2.0503737094055574
            ],
            [
                1.234219656071998,
                1.7094702077258364,
                2.067549790297264
            ],
            [
                1.2494223077078446,
                1.7248526042455072,
                2.08483586110861
            ],
            [
                1.2646173919555208,
                1.7400945031653723,
                2.102042168391322
            ],
            [
                1.2798840154883198,
                1.7553702824642328,
                2.119020799270018
            ],
            [
                1.295230062267708,
                1.7707100476084936,
                2.1360482166124015
            ],
            [
                1.3106394056137776,
                1.7861030137281788,
                2.153436375102936
            ],
            [
                1.3260766948574274,
                1.8015462173801426,
                2.1709624258142406
            ],
            [
                1.3415048666692977,
                1.8170281438737792,
                2.1882651960738895
            ],
            [
                1.3569297917202319,
                1.832447099075359,
                2.205465410702928
            ],
            [
                1.3723726104029046,
                1.847681916852137,
                2.222872141461681
            ],
            [
                1.3878022047500007,
                1.8628522781322896,
                2.2403834380164867
            ],
            [
                1.4031613785491983,
                1.878199708773548,
                2.257676287766683
            ],
            [
                1.4184636042414547,
                1.8936660120694613,
                2.274761194763573
            ],
            [
                1.4337682079500453,
                1.9089790173049528,
                2.291885614220589
            ],
            [
                1.4489990194759812,
                1.9240539406692507,
                2.3090488626355947
            ],
            [
                1.4639611592780783,
                1.93898057821802,
                2.3260207817212732
            ],
            [
                1.4786767254702362,
                1.953761358908212,
                2.3427076242879794
            ],
            [
                1.4934157961443635,
                1.968292057692454,
                2.3591807840403383
            ],
            [
                1.5081598339210585,
                1.9825185504397544,
                2.3754560646787466
            ],
            [
                1.5224609579049944,
                1.9964665197839455,
                2.391456928335359
            ],
            [
                1.5360786199136025,
                2.0101514492501957,
                2.40710748744691
            ],
            [
                1.5492010515793377,
                2.0235595264794957,
                2.422345566958034
            ],
            [
                1.5619573626368233,
                2.036644310455893,
                2.437086941718103
            ],
            [
                1.5742441263416627,
                2.049292841377432,
                2.451194716926695
            ],
            [
                1.5859918839692873,
                2.061382998507539,
                2.464596204631961
            ],
            [
                1.5973184230979458,
                2.0727924069381345,
                2.4774222445956924
            ],
            [
                1.6083188400099737,
                2.083475421856264,
                2.4897995845333614
            ],
            [
                1.618884630430652,
                2.0936663517219705,
                2.501708683153531
            ],
            [
                1.6289048427408916,
                2.103602720713836,
                2.513110491048258
            ],
            [
                1.6384743179363261,
                2.113238385967166,
                2.524030703894592
            ],
            [
                1.6477319648940496,
                2.1224647519930158,
                2.534512502809399
            ],
            [
                1.656719371537761,
                2.1312970539572564,
                2.5445903131016303
            ],
            [
                1.6654398661935548,
                2.139795036477327,
                2.554304275913677
            ],
            [
                1.673881659671505,
                2.148004877729363,
                2.5637651782986914
            ],
            [
                1.6820397807924026,
                2.155978206788293,
                2.573110092113787
            ],
            [
                1.6900543353443789,
                2.163890560645263,
                2.582402157145586
            ],
            [
                1.698138711335667,
                2.17197153869621,
                2.591657388900075
            ],
            [
                1.7063248175787338,
                2.1801750415056196,
                2.6008473640904546
            ],
            [
                1.714512866255206,
                2.188259857062201,
                2.6099183675589077
            ],
            [
                1.7226742548012393,
                2.1961807963626394,
                2.618960412635317
            ],
            [
                1.7308474230944786,
                2.2040755270224874,
                2.6281900710579404
            ],
            [
                1.7390260085852702,
                2.2120148061308234,
                2.637627130819311
            ],
            [
                1.7471515394699475,
                2.219985522076905,
                2.6470633753207573
            ],
            [
                1.7552703705988308,
                2.2280100551292104,
                2.6564432094798756
            ],
            [
                1.7635808618741802,
                2.2361672092443348,
                2.665945455783114
            ],
            [
                1.7721165825662721,
                2.244457958015205,
                2.675614379704815
            ],
            [
                1.7805965426738801,
                2.252736789431338,
                2.685222255050618
            ],
            [
                1.7888689137329499,
                2.260913433389767,
                2.6946415243000437
            ],
            [
                1.7971453177524381,
                2.2690558532658933,
                2.7040330239444397
            ],
            [
                1.8056032153943296,
                2.2772237455515905,
                2.7135339814379527
            ],
            [
                1.8141812930442474,
                2.2853916894196225,
                2.7231021330251357
            ],
            [
                1.8227759625951814,
                2.293519194197149,
                2.7326634364024778
            ],
            [
                NaN,
                NaN,
                NaN
            ],
            [
                NaN,
                NaN,
                NaN
            ],
            [
                NaN,
                NaN,
                NaN
            ],
            [
                NaN,
                NaN,
                NaN
            ],
            [
                NaN,
                NaN,
                NaN
            ],
            [
                NaN,
                NaN,
                NaN
            ],
            [
                NaN,
                NaN,
                NaN
            ],
            [
                NaN,
                NaN,
                NaN
            ],
            [
                NaN,
                NaN,
                NaN
            ],
            [
                NaN,
                NaN,
                NaN
            ],
            [
                NaN,
                NaN,
                NaN
            ],
            [
                NaN,
                NaN,
                NaN
            ],
            [
                NaN,
                NaN,
                NaN
            ],
            [
                NaN,
                NaN,
                NaN
            ],
            [
                NaN,
                NaN,
                NaN
            ],
            [
                NaN,
                NaN,
                NaN
            ],
            [
                NaN,
                NaN,
                NaN
            ],
            [
                NaN,
                NaN,
                NaN
            ],
            [
                NaN,
                NaN,
                NaN
            ],
            [
                NaN,
                NaN,
                NaN
            ],
            [
                NaN,
                NaN,
                NaN
            ],
            [
                NaN,
                NaN,
                NaN
            ],
            [
                NaN,
                NaN,
                NaN
            ],
            [
                NaN,
                NaN,
                NaN
            ],
            [
                NaN,
                NaN,
                NaN
            ],
            [
                NaN,
                NaN,
                NaN
            ],
            [
                NaN,
                NaN,
                NaN
            ],
            [
                NaN,
                NaN,
                NaN
            ],
            [
                NaN,
                NaN,
                NaN
            ],
            [
                NaN,
                NaN,
                NaN
            ],
            [
                NaN,
                NaN,
                NaN
            ],
            [
                NaN,
                NaN,
                NaN
            ],
            [
                NaN,
                NaN,
                NaN
            ],
            [
                NaN,
                NaN,
                NaN
            ],
            [
                NaN,
                NaN,
                NaN
            ],
            [
                NaN,
                NaN,
                NaN
            ],
            [
                NaN,
                NaN,
                NaN
            ],
            [
                NaN,
                NaN,
                NaN
            ],
            [
                NaN,
                NaN,
                NaN
            ],
            [
                NaN,
                NaN,
                NaN
            ],
            [
                NaN,
                NaN,
                NaN
            ],
            [
                NaN,
                NaN,
                NaN
            ],
            [
                NaN,
                NaN,
                NaN
            ],
            [
                NaN,
                NaN,
                NaN
            ],
            [
                NaN,
                NaN,
                NaN
            ],
            [
                NaN,
                NaN,
                NaN
            ],
            [
                NaN,
                NaN,
                NaN
            ],
            [
                NaN,
                NaN,
                NaN
            ],
            [
                NaN,
                NaN,
                NaN
            ],
            [
                NaN,
                NaN,
                NaN
            ],
            [
                NaN,
                NaN,
                NaN
            ],
            [
                NaN,
                NaN,
                NaN
            ],
            [
                NaN,
                NaN,
                NaN
            ],
            [
                NaN,
                NaN,
                NaN
            ],
            [
                NaN,
                NaN,
                NaN
            ],
            [
                NaN,
                NaN,
                NaN
            ],
            [
                NaN,
                NaN,
                NaN
            ],
            [
                NaN,
                NaN,
                NaN
            ],
            [
                NaN,
                NaN,
                NaN
            ],
            [
                NaN,
                NaN,
                NaN
            ],
            [
                NaN,
                NaN,
                NaN
            ],
            [
                NaN,
                NaN,
                NaN
            ],
            [
                NaN,
                NaN,
                NaN
            ],
            [
                NaN,
                NaN,
                NaN
            ],
            [
                NaN,
                NaN,
                NaN
            ],
            [
                NaN,
                NaN,
                NaN
            ],
            [
                NaN,
                NaN,
                NaN
            ],
            [
                NaN,
                NaN,
                NaN
            ],
            [
                NaN,
                NaN,
                NaN
            ],
            [
                NaN,
                NaN,
                NaN
            ],
            [
                NaN,
                NaN,
                NaN
            ]
        ],
        "log_exposure": [
            -3.156219647631507,
            -3.1287686672393504,
            -3.1013176868471937,
            -3.0738667064550365,
            -3.0464157260628797,
            -3.018964745670723,
            -2.991513765278566,
            -2.964062784886409,
            -2.936611804494252,
            -2.9091608241020954,
            -2.8817098437099387,
            -2.854258863317782,
            -2.8268078829256247,
            -2.799356902533468,
            -2.771905922141311,
            -2.7444549417491544,
            -2.717003961356997,
            -2.6895529809648404,
            -2.6621020005726836,
            -2.634651020180527,
            -2.60720003978837,
            -2.5797490593962134,
            -2.552298079004056,
            -2.5248470986118994,
            -2.4973961182197426,
            -2.4699451378275854,
            -2.4424941574354286,
            -2.415043177043272,
            -2.387592196651115,
            -2.3601412162589583,
            -2.3326902358668016,
            -2.3052392554746444,
            -2.2777882750824876,
            -2.250337294690331,
            -2.2228863142981736,
            -2.195435333906017,
            -2.16798435351386,
            -2.1405333731217033,
            -2.113082392729546,
            -2.0856314123373894,
            -2.0581804319452326,
            -2.030729451553076,
            -2.003278471160919,
            -1.9758274907687619,
            -1.948376510376605,
            -1.9209255299844483,
            -1.8934745495922916,
            -1.8660235692001343,
            -1.8385725888079776,
            -1.8111216084158208,
            -1.783670628023664,
            -1.7562196476315073,
            -1.72876866723935,
            -1.7013176868471933,
            -1.673866706455036,
            -1.6464157260628793,
            -1.6189647456707226,
            -1.5915137652785658,
            -1.564062784886409,
            -1.5366118044942518,
            -1.509160824102095,
            -1.4817098437099383,
            -1.4542588633177815,
            -1.4268078829256243,
            -1.3993569025334676,
            -1.3719059221413108,
            -1.344454941749154,
            -1.3170039613569973,
            -1.28955298096484,
            -1.2621020005726833,
            -1.2346510201805265,
            -1.2072000397883698,
            -1.1797490593962126,
            -1.1522980790040558,
            -1.124847098611899,
            -1.0973961182197423,
            -1.069945137827585,
            -1.0424941574354283,
            -1.0150431770432715,
            -0.9875921966511146,
            -0.9601412162589574,
            -0.9326902358668008,
            -0.905239255474644,
            -0.8777882750824874,
            -0.8503372946903306,
            -0.8228863142981736,
            -0.7954353339060168,
            -0.7679843535138601,
            -0.7405333731217033,
            -0.7130823927295465,
            -0.6856314123373893,
            -0.6581804319452326,
            -0.6307294515530758,
            -0.603278471160919,
            -0.5758274907687617,
            -0.548376510376605,
            -0.5209255299844482,
            -0.4934745495922914,
            -0.46602356920013466,
            -0.43857258880797745,
            -0.4111216084158207,
            -0.3836706280236639,
            -0.35621964763150715,
            -0.32876866723934994,
            -0.3013176868471932,
            -0.2738667064550363,
            -0.24641572606287954,
            -0.21896474567072277,
            -0.19151376527856556,
            -0.1640627848864088,
            -0.13661180449425203,
            -0.10916082410209527,
            -0.08170984370993856,
            -0.05425886331778135,
            -0.026807882925624582,
            0.0006430974665321831,
            0.02809407785868895,
            0.0555450582508461,
            0.08299603864300287,
            0.11044701903515969,
            0.13789799942731645,
            0.1653489798194732,
            0.1927999602116304,
            0.22025094060378717,
            0.24770192099594393,
            0.27515290138810067,
            0.302603881780258,
            0.33005486217241475,
            0.3575058425645715,
            0.3849568229567283,
            0.41240780334888505,
            0.43985878374104226,
            0.4673097641331989,
            0.4947607445253557,
            0.5222117249175124,
            0.5496627053096697,
            0.5771136857018264,
            0.6045646660939832,
            0.63201564648614,
            0.6594666268782967,
            0.6869176072704539,
            0.7143685876626107,
            0.7418195680547675,
            0.7692705484469242,
            0.7967215288390814,
            0.8241725092312382,
            0.851623489623395,
            0.8790744700155517,
            0.9065254504077085,
            0.9339764307998653,
            0.961427411192022,
            0.9888783915841797,
            1.0163293719763364,
            1.0437803523684932,
            1.0712313327606497,
            1.0986823131528065,
            1.1261332935449633,
            1.1535842739371205,
            1.1810352543292773,
            1.208486234721434,
            1.2359372151135917,
            1.2633881955057484,
            1.2908391758979052,
            1.318290156290062,
            1.3457411366822187,
            1.3731921170743755,
            1.4006430974665323,
            1.428094077858689,
            1.4555450582508458,
            1.4829960386430026,
            1.5104470190351602,
            1.537897999427317,
            1.5653489798194737,
            1.5927999602116305,
            1.6202509406037873,
            1.647701920995944,
            1.6751529013881008,
            1.7026038817802576,
            1.7300548621724143,
            1.757505842564572,
            1.7849568229567288,
            1.812407803348885,
            1.8398587837410418,
            1.8673097641331986,
            1.8947607445253554,
            1.9222117249175121,
            1.949662705309669,
            1.977113685701826,
            2.0045646660939838,
            2.0320156464861405,
            2.0594666268782973,
            2.086917607270454,
            2.114368587662611,
            2.1418195680547676,
            2.169270548446924,
            2.1967215288390807,
            2.2241725092312374,
            2.251623489623395,
            2.279074470015552,
            2.3065254504077086,
            2.3339764307998654,
            2.361427411192022,
            2.388878391584179,
            2.4163293719763357,
            2.4437803523684924,
            2.471231332760649,
            2.498682313152807,
            2.5261332935449636,
            2.5535842739371204,
            2.581035254329277,
            2.608486234721434,
            2.6359372151135907,
            2.6633881955057475,
            2.6908391758979042,
            2.718290156290061,
            2.7457411366822186,
            2.7731921170743754,
            2.800643097466532,
            2.828094077858689,
            2.8555450582508457,
            2.8829960386430025,
            2.9104470190351592,
            2.937897999427316,
            2.9653489798194728,
            2.9927999602116295,
            3.020250940603787,
            3.047701920995944,
            3.0751529013881007,
            3.1026038817802575,
            3.1300548621724142,
            3.157505842564571,
            3.1849568229567278,
            3.2124078033488845,
            3.2398587837410413,
            3.267309764133199,
            3.2947607445253557,
            3.3222117249175125,
            3.3496627053096693,
            3.377113685701826,
            3.404564666093983,
            3.4320156464861395,
            3.4594666268782963,
            3.486917607270453,
            3.5143685876626107,
            3.5418195680547675,
            3.5692705484469243,
            3.596721528839081,
            3.624172509231238,
            3.6516234896233946,
            3.6790744700155513,
            3.706525450407708,
            3.733976430799865,
            3.7614274111920225,
            3.7888783915841793,
            3.8163293719763365,
            3.8437803523684932
        ],
        "dye_density": [
            [
                NaN,
                NaN,
                NaN,
                NaN,
                NaN
            ],
            [
                0.28224857399797143,
                0.04693278549192424,
                0.32301300451080484,
                NaN,
                NaN
            ],
            [
                0.2552713155680667,
                0.04005334407439767,
                0.4691446455479718,
                0.767083308431127,
                1.291807638603556
            ],
            [
                0.2048823943808031,
                0.03921330390718004,
                0.6189085703098265,
                0.786500795129956,
                1.3787550905686579
            ],
            [
                0.16494957376801425,
                0.043251330807982394,
                0.7673890920238411,
                0.8808645089509348,
                1.5778466611062685
            ],
            [
                0.13370596618538477,
                0.04926130417629074,
                0.8985431101617559,
                0.9530477892594885,
                1.7569605603517235
            ],
            [
                0.10910651892856102,
                0.05628229899395858,
                0.9758912808231534,
                0.9851565001733297,
                1.8286139703352324
            ],
            [
                0.08903357571930649,
                0.06506574863762334,
                0.9990864480323267,
                0.9708530905816336,
                1.8301801052239361
            ],
            [
                0.07503563842858825,
                0.08999168693901533,
                0.9572381129745644,
                0.9193340130832564,
                1.7768652990131297
            ],
            [
                0.06410451871533776,
                0.12943677686487978,
                0.8544025191062516,
                0.8529331176527102,
                1.6684724111769016
            ],
            [
                0.05413082916573078,
                0.1824168869482157,
                0.7063373970741866,
                0.7799898046922207,
                1.5295655314020344
            ],
            [
                0.04654807909499127,
                0.27904351525123455,
                0.5485659782138327,
                0.7114097531989478,
                1.4137983223534543
            ],
            [
                0.04237147555210187,
                0.40024125682707684,
                0.3990258133625877,
                0.6698591160390468,
                1.377208530573314
            ],
            [
                0.04184611853108646,
                0.554970423772749,
                0.27283125632914884,
                0.6567029114830326,
                1.3972659332731387
            ],
            [
                0.04691081308716511,
                0.700709729539164,
                0.18290482775650624,
                0.6461331497580262,
                1.437182915584292
            ],
            [
                0.05594952567369529,
                0.8356694432532904,
                0.12253485614986225,
                0.6421709016062913,
                1.4800353116163565
            ],
            [
                0.0720983220846576,
                0.9357896135767002,
                0.08164677748527989,
                0.6440562117395269,
                1.5121473724833514
            ],
            [
                0.09471824091545289,
                0.9937247486778799,
                0.055937624002476004,
                0.6376311853857544,
                1.4723355924840882
            ],
            [
                0.12336798089382138,
                0.9718853371063018,
                0.0408404167940468,
                0.6258161181039303,
                1.3516091338003122
            ],
            [
                0.15937142959919798,
                0.893752052283458,
                0.030388800891659046,
                0.5909339621270294,
                1.1665789889638751
            ],
            [
                0.20586517684774217,
                0.7625037936078256,
                0.023833757554252082,
                0.5109576616263114,
                0.9719289823288263
            ],
            [
                0.26730981581024493,
                0.5948999423943411,
                0.019299121741842326,
                0.39762462282539573,
                0.8258142925900811
            ],
            [
                0.3388401967266463,
                0.4327267510688431,
                0.016120334550845914,
                0.3081465105024408,
                0.7389625108841452
            ],
            [
                0.4152482028725558,
                0.3027209843571191,
                0.015391115598528887,
                0.25660660842093164,
                0.7193851100179778
            ],
            [
                0.5005911861712049,
                0.20515155799835197,
                0.013587680070708598,
                0.23483196242497245,
                0.7470068259324644
            ],
            [
                0.5856670191971101,
                0.14253075120413483,
                0.009601310394461205,
                0.23088190479807924,
                0.8010278521289192
            ],
            [
                0.6726974229685206,
                0.10388106984392072,
                0.004000774217521752,
                0.2370526408790511,
                0.8749694836223331
            ],
            [
                0.7583502429455593,
                0.0755841319300358,
                0.0011150756080241272,
                0.24909100673315873,
                0.9511757217662602
            ],
            [
                0.8374776148978634,
                0.0597410031334923,
                -0.0005764752606348977,
                0.26388586644626494,
                1.0279406521109231
            ],
            [
                0.9096167724126918,
                0.04953967570126168,
                -0.0013038699726981111,
                0.278704533428052,
                1.0902058392564797
            ],
            [
                0.9647666118275269,
                0.041904129349914644,
                -0.0012969968112342247,
                0.29142607344594706,
                1.1503445525454514
            ],
            [
                0.9861270803938307,
                0.036664661615591794,
                -0.0007857440593119509,
                0.3006956576585849,
                1.1743632688534753
            ],
            [
                0.9939642142582097,
                0.03340840891250732,
                0.0,
                0.30245048478236336,
                1.1708904082131635
            ],
            [
                0.9676329012516397,
                0.03180230898111845,
                0.0008303470836329164,
                NaN,
                NaN
            ],
            [
                0.9034761891993082,
                0.03052347014581009,
                0.0014754089085180864,
                NaN,
                NaN
            ],
            [
                0.813300936711092,
                0.03059230743124825,
                0.001705297191586798,
                NaN,
                NaN
            ],
            [
                0.7077142240998846,
                0.029365922210930737,
                0.0012901236497703402,
                NaN,
                NaN
            ],
            [
                NaN,
                0.028086758983920972,
                0.0,
                NaN,
                NaN
            ],
            [
                NaN,
                NaN,
                NaN,
                NaN,
                NaN
            ],
            [
                NaN,
                NaN,
                NaN,
                NaN,
                NaN
            ],
            [
                NaN,
                NaN,
                NaN,
                NaN,
                NaN
            ]
        ],
        "tune": {
            "gamma_factor": 1.0,
            "dye_density_min_factor": 1.0,
            "gamma_correction": [
                1.0,
                1.0,
                1.0
            ],
            "log_exposure_correction": [
                0.0,
                0.0,
                0.0
            ]
        },
        "density_curves_layers": [
            0,
            3,
            3
        ]
    },
    "parametric": {
        "density_curves": {
            "active": false,
            "gamma": [
                0.7,
                0.7,
                0.7
            ],
            "log_exposure_0": [
                -1.4,
                -1.4,
                -1.52
            ],
            "density_max": [
                2.75,
                2.75,
                2.84
            ],
            "toe_size": [
                0.3,
                0.3,
                0.3
            ],
            "shoulder_size": [
                0.85,
                0.85,
                0.85
            ]
        }
    },
    "glare": {
        "active": false,
        "percent": 0.0,
        "roughness": 0.25,
        "blur": 0.5
    },
    "grain": {
        "active": true,
        "sublayers_active": true,
        "agx_particle_area_um2": 0.2,
        "agx_particle_scale": [
            0.8,
            1,
            2
        ],
        "agx_particle_scale_layers": [
            2.5,
            1,
            0.5
        ],
        "density_min": [
            0.07,
            0.08,
            0.12
        ],
        "uniformity": [
            0.97,
            0.97,
            0.99
        ],
        "blur": 0.55,
        "blur_dye_clouds_um": 1.0,
        "n_sub_layers": 1
    },
    "halation": {
        "active": true,
        "strength": [
            0.08,
            0.005,
            0.001
        ],
        "size_um": [
            200,
            200,
            200
        ],
        "scattering_strength": [
            0.01,
            0.02,
            0.04
        ],
        "scattering_size_um": [
            30,
            20,
            15
        ]
    },
    "dir_couplers": {
        "active": true,
        "amount_rgb": [
            1.0,
            1.0,
            1.0
        ],
        "diffusion_interlayer": 2.0,
        "diffusion_size_um": 10.0,
        "high_exposure_shift": 0.0
    },
    "masking_couplers": {
        "cross_over_points": [
            585,
            510,
            200
        ],
        "transition_widths": [
            15,
            15,
            1
        ],
        "gaussian_model": [
            [
                [
                    435,
                    20,
                    0.09
                ],
                [
                    560,
                    20,
                    0.09
                ]
            ],
            [
                [
                    470,
                    20,
                    0.09
                ]
            ],
            [
                [
                    520,
                    20,
                    0.09
                ]
            ]
        ]
    }
}